PyKLU/klu.py
PyKLU/klu_interf.c
PyKLU/klu_interf.h
PyKLU/_klu.c
PyKLU/_klu.cp39-win_amd64.pyd
PyKLU/_klu.pxd
PyKLU/_klu.pyi
PyKLU/_klu.pyx
PyKLU/_test_helpers.py
PyKLU/_version.py
PyKLU/__init__.py
pyklu-0.2.0.dist-info/DELVEWHEEL
pyklu-0.2.0.dist-info/METADATA
pyklu-0.2.0.dist-info/RECORD
pyklu-0.2.0.dist-info/top_level.txt
pyklu-0.2.0.dist-info/WHEEL
pyklu-0.2.0.dist-info/licenses/LICENSE.txt
pyklu-0.2.0.dist-info/licenses/LICENSE_SuiteSparse.txt
pyklu.libs/.load-order-pyklu-0.2.0
pyklu.libs/amd-af2365820cabbceca57b552503277eef.dll
pyklu.libs/btf-80e71009eb2b45415c8eb90ea26dde28.dll
pyklu.libs/colamd-6d288d6151be26aaf21d8f11bbdae483.dll
pyklu.libs/klu-cef5c447e4f1dff10d7665280100c6d9.dll
pyklu.libs/suitesparseconfig-3bbb4770beeb54f9659a7e70a01b4598.dll
pyklu.libs/vcomp140-e7e50211906ab1c6226a3133fda8d8c8.dll
