Metadata-Version: 2.4
Name: PyKLU
Version: 0.2.0
Summary: Python bindings for the SuiteSparse KLU sparse linear solver
Author-email: Evangelos Katralis <evangelos.katralis@cern.ch>, Giovanni Iadarola <giovanni.iadarola@cern.ch>
License-Expression: LGPL-2.1-or-later
Project-URL: Homepage, https://github.com/ekatralis/PyKLU
Project-URL: Source, https://github.com/ekatralis/PyKLU
Project-URL: Issues, https://github.com/ekatralis/PyKLU/issues
Project-URL: License (SuiteSparse), https://github.com/DrTimothyAldenDavis/SuiteSparse/blob/stable/LICENSE.txt
Classifier: Development Status :: 4 - Beta
Classifier: Intended Audience :: Science/Research
Classifier: Intended Audience :: Developers
Classifier: Topic :: Scientific/Engineering
Classifier: Topic :: Scientific/Engineering :: Mathematics
Classifier: Programming Language :: Python :: 3
Classifier: Programming Language :: Python :: 3 :: Only
Classifier: Programming Language :: Python :: 3.9
Classifier: Programming Language :: Python :: 3.10
Classifier: Programming Language :: Python :: 3.11
Classifier: Programming Language :: Python :: 3.12
Classifier: Programming Language :: Python :: 3.13
Classifier: Programming Language :: Python :: 3.14
Classifier: Operating System :: POSIX :: Linux
Classifier: Operating System :: MacOS :: MacOS X
Classifier: Operating System :: Microsoft :: Windows
Requires-Python: >=3.9
License-File: LICENSE.txt
License-File: LICENSE_SuiteSparse.txt
Requires-Dist: numpy
Requires-Dist: scipy
Provides-Extra: dev
Requires-Dist: pytest; extra == "dev"
Dynamic: license-file
